synccord/__init__.py
synccord/main.py
synccord-0.1.0.dist-info/METADATA
synccord-0.1.0.dist-info/WHEEL
synccord-0.1.0.dist-info/top_level.txt
synccord-0.1.0.dist-info/RECORD
