Metadata-Version: 2.1
Name: synccord
Version: 0.1.0
Summary: A firefly developer tools for AI integration
Author: Jane Doe
Author-email: JanDoe237@gmail.com
Classifier: Programming Language :: Python :: 3
Classifier: License :: OSI Approved :: MIT License
Classifier: Operating System :: Microsoft :: Windows
Requires-Python: >=3.6
Requires-Dist: pywinauto
